README.md
setup.py
netbox_network_importer/__init__.py
netbox_network_importer/__main__.py
netbox_network_importer/config.py
netbox_network_importer/helper.py
netbox_network_importer/logging_config.py
netbox_network_importer.egg-info/PKG-INFO
netbox_network_importer.egg-info/SOURCES.txt
netbox_network_importer.egg-info/dependency_links.txt
netbox_network_importer.egg-info/entry_points.txt
netbox_network_importer.egg-info/not-zip-safe
netbox_network_importer.egg-info/requires.txt
netbox_network_importer.egg-info/top_level.txt
netbox_network_importer/connections/Napalm.py
netbox_network_importer/connections/Netbox.py
netbox_network_importer/connections/Nornir.py
netbox_network_importer/connections/PyAts.py
netbox_network_importer/connections/__init__.py
netbox_network_importer/data_converter/__init__.py
netbox_network_importer/data_converter/network_to_netbox.py
netbox_network_importer/helpers/__init__.py
netbox_network_importer/helpers/batch_query.py
netbox_network_importer/helpers/error_handling.py
netbox_network_importer/helpers/result_factory.py
netbox_network_importer/netbox_updater/__init__.py
netbox_network_importer/netbox_updater/bandwidth.py
netbox_network_importer/netbox_updater/facts.py
netbox_network_importer/netbox_updater/interfaces.py
netbox_network_importer/netbox_updater/interfaces_ips.py
netbox_network_importer/netbox_updater/interfaces_vlans.py
netbox_network_importer/netbox_updater/lag_interfaces.py
netbox_network_importer/outputers/__init__.py
netbox_network_importer/outputers/output.py
netbox_network_importer/processors/__init__.py
netbox_network_importer/processors/progress_indicator.py
netbox_network_importer/processors/save_netbox_results.py
netbox_network_importer/pyats/__init__.py
netbox_network_importer/pyats/parser.py
netbox_network_importer/results/__init__.py
netbox_network_importer/results/results.py
netbox_network_importer/tasks/__init__.py
netbox_network_importer/tasks/connection_test.py
netbox_network_importer/tasks/synchronizer.py