Metadata-Version: 2.4
Name: netbox_network_importer
Version: 1.1.7
Summary: Poll data from devices and store them into Netbox
Home-page: https://gitlab.cesnet.cz/701/done/netbox_network_importer
Author: Jan Krupa
Author-email: jan.krupa@cesnet.cz
Keywords: netbox,network
Classifier: Programming Language :: Python :: 3 :: Only
Classifier: Intended Audience :: Developers
Classifier: Development Status :: 4 - Beta
Classifier: Operating System :: Unix
Requires-Python: >=3.6, <4
Requires-Dist: click
Requires-Dist: pynetbox==7.4.1
Requires-Dist: python-slugify
Requires-Dist: appdirs
Requires-Dist: pyyaml
Requires-Dist: python-dotenv
Requires-Dist: pyats[full]==25.2
Requires-Dist: netutils
Requires-Dist: nornir==3.5.0
Requires-Dist: nornir-netbox
Requires-Dist: nornir_utils
Requires-Dist: nornir_rich
Requires-Dist: deepdiff
Requires-Dist: napalm==5.0.0
Requires-Dist: ncclient
Requires-Dist: loguru
Requires-Dist: dictdiffer
Requires-Dist: json2html
Requires-Dist: jsonpickle
Dynamic: author
Dynamic: author-email
Dynamic: classifier
Dynamic: description
Dynamic: description-content-type
Dynamic: home-page
Dynamic: keywords
Dynamic: requires-dist
Dynamic: requires-python
Dynamic: summary
